arduino_hooks/__init__.py
arduino_hooks/arduino_cli.py
arduino_hooks/arduino_lint.py
arduino_hooks-0.3.0.dist-info/LICENSE.md
arduino_hooks-0.3.0.dist-info/METADATA
arduino_hooks-0.3.0.dist-info/WHEEL
arduino_hooks-0.3.0.dist-info/entry_points.txt
arduino_hooks-0.3.0.dist-info/top_level.txt
arduino_hooks-0.3.0.dist-info/RECORD
