Metadata-Version: 2.1
Name: arduino-hooks
Version: 0.3.0
Summary: Arduino tooling hooks for use with the pre-commit framework.
Home-page: https://github.com/CreatingNull/arduino-hooks
Author: Steve Richardson
Author-email: steve.public@nulltek.xyz
License: MIT
Classifier: License :: OSI Approved :: MIT License
Classifier: Programming Language :: Python :: 3
Classifier: Programming Language :: Python :: 3 :: Only
Classifier: Programming Language :: Python :: 3.8
Classifier: Programming Language :: Python :: 3.9
Classifier: Programming Language :: Python :: 3.10
Classifier: Programming Language :: Python :: 3.11
Requires-Python: >=3.8
License-File: LICENSE.md
Requires-Dist: clipy-hooks (>=0.1.1)
